LICENSE
README.md
pyproject.toml
examples/demo.py
extapi/__init__.py
extapi/_helpers.py
extapi/_meta.py
extapi/py.typed
extapi.egg-info/PKG-INFO
extapi.egg-info/SOURCES.txt
extapi.egg-info/dependency_links.txt
extapi.egg-info/requires.txt
extapi.egg-info/top_level.txt
extapi/http/__init__.py
extapi/http/abc.py
extapi/http/types.py
extapi/http/addons/__init__.py
extapi/http/addons/auth.py
extapi/http/addons/headers.py
extapi/http/addons/log.py
extapi/http/addons/retry.py
extapi/http/addons/status.py
extapi/http/backends/__init__.py
extapi/http/backends/aiohttp.py
extapi/http/backends/httpx.py
extapi/http/executors/__init__.py
extapi/http/executors/limiters.py
extapi/http/executors/metrics.py
extapi/http/executors/retry.py
extapi/http/executors/trace.py
extapi/http/executors/wrapped.py
extapi/http/metrics/__init__.py
extapi/http/metrics/container.py
extapi/http/metrics/helpers.py
extapi/limiters/__init__.py
extapi/limiters/concurrency/__init__.py
extapi/limiters/concurrency/abc.py
extapi/limiters/concurrency/local.py
extapi/limiters/rps/__init__.py
extapi/limiters/rps/abc.py
extapi/limiters/rps/local.py