Metadata-Version: 2.1
Name: extapi
Version: 0.1.7
Summary: External API library
Author-email: KTS <hello@kts.tech>
License:                                  Apache License
Classifier: Development Status :: 5 - Production/Stable
Classifier: Framework :: AsyncIO
Classifier: Operating System :: POSIX
Classifier: Operating System :: MacOS :: MacOS X
Classifier: Operating System :: Microsoft :: Windows
Classifier: Programming Language :: Python :: 3.10
Classifier: Programming Language :: Python :: 3.11
Classifier: Programming Language :: Python :: 3.12
Classifier: Intended Audience :: Developers
Classifier: Topic :: Software Development :: Libraries :: Python Modules
Requires-Python: >=3.10.0
License-File: LICENSE
Requires-Dist: multidict
Requires-Dist: yarl
Requires-Dist: typing-extensions; python_version < "3.11"
Provides-Extra: aiohttp
Requires-Dist: aiohttp; extra == "aiohttp"
Provides-Extra: httpx
Requires-Dist: httpx; extra == "httpx"
Provides-Extra: opentelemetry
Requires-Dist: opentelemetry-api; extra == "opentelemetry"
Requires-Dist: opentelemetry-semantic-conventions; extra == "opentelemetry"
Provides-Extra: prometheus
Requires-Dist: prometheus_client; extra == "prometheus"
Provides-Extra: tests
Requires-Dist: pytest; extra == "tests"
Requires-Dist: pytest-asyncio; extra == "tests"
Requires-Dist: pytest-aiohttp; extra == "tests"
Requires-Dist: pytest-mock; extra == "tests"
Requires-Dist: coverage; extra == "tests"
Requires-Dist: mypy; extra == "tests"
Requires-Dist: ruff; extra == "tests"
Requires-Dist: deptry; extra == "tests"
Requires-Dist: opentelemetry-sdk; extra == "tests"
